{
  "mainNavigation": [
    { "href": "/", "label": "Home" },
    { "href": "/about-us", "label": "About" },
    { "href": "/services", "label": "Services" },
    {
      "href": "/members",
      "label": "Members",
      "subLinks": [
        { "href": "/members?department=Officers", "label": "Officers" },
        { "href": "/members?department=Front-End", "label": "Front-End" },
        { "href": "/members?department=Back-End", "label": "Back-End" },
        { "href": "/members?department=Full-Stack", "label": "Full-Stack" },
        { "href": "/members?department=UI%2FUX", "label": "UI/UX" },
        { "href": "/members?department=DevOps", "label": "DevOps" },
        { "href": "/members?department=QA", "label": "QA" },
        { "href": "/members?department=Creatives", "label": "Creatives" }
      ]
    },
    { "href": "/contact-us", "label": "Contact" },
    { "href": "/projects", "label": "Projects" }
  ],
  "socialMedia": [
    { "type": "email", "href": "mailto:samahan.sd@addu.edu.ph", "label": "Email" },
    { "type": "linkedin", "href": "https://linkedin.com/company/samahan-sysdev", "label": "LinkedIn" },
    { "type": "facebook", "href": "https://facebook.com/samahansysdev", "label": "Facebook" }
  ]
}